PyFaceCrop/__init__.py
PyFaceCrop/face_crop.py
PyFaceCrop/main.py
PyFaceCrop/tester.py
PyFaceCrop/haarcascades/haarcascade_eye.xml
PyFaceCrop/haarcascades/haarcascade_frontalface_default.xml
PyFaceCrop/screenshots/__init__.py
pyfacecrop-0.0.25.dist-info/licenses/LICENSE
pyfacecrop-0.0.25.dist-info/METADATA
pyfacecrop-0.0.25.dist-info/WHEEL
pyfacecrop-0.0.25.dist-info/top_level.txt
pyfacecrop-0.0.25.dist-info/RECORD
