Metadata-Version: 2.4
Name: PyFaceCrop
Version: 0.0.25
License-File: LICENSE
Requires-Dist: opencv-python
Dynamic: description
Dynamic: description-content-type
Dynamic: license-file
Dynamic: requires-dist
